{
  "schema_version": "1.0",
  "ID": "scan-1760971294947373885",
  "Target": {
    "Root": "example.com",
    "Mode": "active",
    "Scope": {
      "IncludeSubdomains": true,
      "MaxDepth": 0,
      "OnlyInScope": true
    },
    "Tags": [],
    "Metadata": {}
  },
  "Artifacts": [
    {
      "id": "fa1e5f855745e76b",
      "type": "ip",
      "value": "23.215.0.138",
      "sources": [
        "httpx"
      ],
      "confidence": 1,
      "discovered_at": "2025-10-20T16:41:35.60807738+02:00"
    },
    {
      "id": "248875e3afb28cac",
      "type": "url",
      "value": "https://example.com",
      "sources": [
        "httpx"
      ],
      "confidence": 1,
      "discovered_at": "2025-10-20T16:41:35.603202715+02:00"
    }
  ],
  "Metadata": {
    "StartTime": "2025-10-20T16:41:34.947374184+02:00",
    "EndTime": "2025-10-20T16:41:35.608194378+02:00",
    "duration_ns": 660820213,
    "duration": "660.820213ms",
    "SourcesUsed": null,
    "TotalSources": 1,
    "TotalRelations": 0,
    "RelationsByType": {},
    "Version": "b8bedfe-dirty",
    "Environment": {
      "commit": "b8bedfe",
      "date": "2025-10-20T14:41:34Z"
    }
  },
  "Warnings": [],
  "Errors": []
}
